mytorch/__init__.py
mytorch-0.1.0.dev0.dist-info/METADATA
mytorch-0.1.0.dev0.dist-info/RECORD
mytorch-0.1.0.dev0.dist-info/WHEEL
mytorch-0.1.0.dev0.dist-info/top_level.txt
